cfmeta/__init__.py
cfmeta/cmip3file.py
cfmeta/cmip5file.py
cfmeta/cmipfile.py
cfmeta/exceptions.py
cfmeta/path.py
cfmeta-0.2.1.dist-info/DESCRIPTION.rst
cfmeta-0.2.1.dist-info/METADATA
cfmeta-0.2.1.dist-info/RECORD
cfmeta-0.2.1.dist-info/WHEEL
cfmeta-0.2.1.dist-info/metadata.json
cfmeta-0.2.1.dist-info/top_level.txt
cfmeta-0.2.1.dist-info/zip-safe
