Metadata-Version: 2.0
Name: cfmeta
Version: 0.2.1
Summary: Utility for processing CF metadata
Home-page: https://github.com/pacificclimate/cfmeta
Author: Basil Veerman
Author-email: bveerman@uvic.ca
License: GPL-3.0
Keywords: climate forecast cf cmor cmip5 cmip3
Platform: UNKNOWN
Classifier: Development Status :: 3 - Alpha
Classifier: Intended Audience :: Developers
Classifier: Intended Audience :: Science/Research
Classifier: License :: OSI Approved :: GNU General Public License v3 (GPLv3)
Classifier: Natural Language :: English
Classifier: Programming Language :: Python :: 2.7
Classifier: Programming Language :: Python :: 3.4
Provides-Extra: netCDF
Requires-Dist: netCDF4; extra == 'netCDF'
